algebrax/__init__.py
algebrax/analysis.py
algebrax/automata.py
algebrax/converters.py
algebrax/group.py
algebrax/lattice.py
algebrax/probability.py
algebrax/semiring.py
algebrax/sparsity.py
algebrax/transforms.py
algebrax/trie.py
algebrax/typing.py
algebrax/matrix/__init__.py
algebrax/matrix/academic.py
algebrax/matrix/core.py
algebrax-0.1.0.dist-info/METADATA
algebrax-0.1.0.dist-info/WHEEL
algebrax-0.1.0.dist-info/licenses/LICENSE
algebrax-0.1.0.dist-info/RECORD
